{
  "text": "This conversation has just started. There is no text to summarize yet. What would you like to talk about? I can summarize our conversation at the end if you'd like.",
  "content": "ASSISTANT: [TOOL: Bash]",
  "namespace": "scripty",
  "username": "wolf",
  "session": "c2917c9c-32f3-45db-afb0-553c39fb6eef",
  "timestamp": "2025-12-29T09:34:29.403375",
  "keywords": [
    "assistant \n\nassistant: bash",
    "assistant",
    "tool"
  ],
  "sentiment": {
    "score": 4,
    "analysis": "In this specific instance, there is no sentiment as such in the provided text since it only states the name of a computer programming language (Bash) and does not contain any dialogue or emotional content. However, if we were to rate the overall context based on the assumption that the user might be interested or positive about learning or working with Bash, I would rate it 4 out of 5, as having knowledge of Bash is useful in various areas of computer science and system administration."
  },
  "source": "swarm-intake"
}