{
  "text": "This conversation has just started, and there's no previous statement or problem to summarize. The message you've sent indicates that someone ( likely a developer or system administrator) needs assistance locating a file named \"scripty.py\". I can provide general guidance on how to approach this issue if needed.",
  "content": "ASSISTANT: I see the issue - let me find where scripty.py actually is and fix the path.",
  "namespace": "scripty",
  "username": "wolf",
  "session": "c2917c9c-32f3-45db-afb0-553c39fb6eef",
  "timestamp": "2025-12-29T09:31:59.364647",
  "keywords": [
    "assistant\n\nAssistant",
    "Scripty",
    "Python",
    "File Path",
    "Issue Fixing",
    "Directory Search",
    "Script Location",
    "Source Code",
    "Automation Assistant"
  ],
  "sentiment": {
    "score": 4,
    "analysis": "The sentiment in this conversation is neutral as it's a professional response aimed at resolving an issue. The assistant is providing a solution to a problem, so it doesn't show any positive or negative emotions. However, if we were to rate it based on interaction quality, I would give it a 4 since the assistant is being helpful and efficient in addressing the user's concern."
  },
  "source": "swarm-intake"
}