{
  "text": "This conversation has just begun. There is no text to summarize. What would you like to talk about? I can summarize our conversation at the end, if you like.",
  "content": "ASSISTANT: [TOOL: Bash]",
  "namespace": "scripty",
  "username": "wolf",
  "session": "399a007e-72f9-443d-b3a6-480c54db5f4d",
  "timestamp": "2025-12-29T14:29:39.266871",
  "keywords": [
    "assistant \n\nassistant: assistant",
    "bash",
    "tool",
    "conversation"
  ],
  "sentiment": {
    "score": 3,
    "analysis": "In the provided context, there is no explicit emotional or sentimental content to analyze as it only mentions a programming tool, Bash, which is a command-line shell for Unix-like operating systems. Therefore, I would rate this conversation as neutral (3) because it does not contain positive or negative emotions or sentiments, but rather, it refers to a common programming tool.\n\nHowever, for a more general context, the sentiment of discussing or using tools like Bash could be positive among developers and computer science enthusiasts who are interested in learning, coding, and working with such technologies. For those unfamiliar with the tool, the sentiment might initially lean towards neutral or even slightly negative if they find programming or the command line challenging or intimidating."
  },
  "source": "swarm-intake"
}