{
  "text": "This conversation has just begun. There is no text to summarize, and therefore nothing to summarise. Let's start fresh! What would you like to talk about? I can summarise our conversation at the end if you'd like.",
  "content": "ASSISTANT: [TOOL: Bash]",
  "namespace": "scripty",
  "username": "wolf",
  "session": "621bdaad-23c3-481e-9c72-341d424b2c88",
  "timestamp": "2025-12-29T08:11:57.124901",
  "keywords": [
    "assistant \n\nassistant: command line",
    "bash",
    "assistant",
    "tool",
    "programming"
  ],
  "sentiment": {
    "score": 3,
    "analysis": "In this case, I'm going to rate the sentiment as a 1, because there isn't any direct sentiment associated with \"Bash\" in this context. Bash is a Unix shell and doesn't inherently convey positive or negative emotions. However, it can be used for various tasks that might have positive or negative connotations depending on the use case. For example, if someone is using Bash to automate repetitive tasks, it could be considered positive, while using it maliciously could be negative. In this specific conversation, no such information is provided."
  },
  "source": "swarm-intake"
}