{
  "text": "This conversation has just started, and I have no information to summarize. The text \"ASSISTANT: [TOOL: Bash]\" appears to be a message or instruction received by the Assistant, likely from Bash, a command-line shell or scripting language. Since we haven't discussed anything yet, there's nothing for me to summarize.",
  "content": "ASSISTANT: [TOOL: Bash]",
  "namespace": "scripty",
  "username": "wolf",
  "session": "c2917c9c-32f3-45db-afb0-553c39fb6eef",
  "timestamp": "2025-12-29T09:45:59.602905",
  "keywords": [
    "assistant \n\nassistant: bash",
    "assistant",
    "tool",
    "software"
  ],
  "sentiment": {
    "score": 3,
    "analysis": "In this specific instance, there is no clear sentiment as the text is a statement about a tool (Bash), which is a programming language commonly used in Unix-like operating systems. There's no emotional tone or explicit evaluation of the tool, so it would be challenging to assign a rating. However, if we were to consider that Bash is generally well-regarded and widely adopted within its intended use case, we could say it implicitly carries a positive sentiment. Yet, without context or additional information about the conversation, this assessment remains tentative."
  },
  "source": "swarm-intake"
}