{
  "text": "This conversation has just begun, and I haven't received any text to summarize yet. My apologies for the confusion. If you'd like to share a story or ask a question, I'm here to help!",
  "content": "ASSISTANT: Still restarting. Let me check what's wrong now:",
  "namespace": "scripty",
  "username": "wolf",
  "session": "399a007e-72f9-443d-b3a6-480c54db5f4d",
  "timestamp": "2025-12-29T11:40:32.428058",
  "keywords": [
    "Here are the extracted keywords:\n\nRestarting",
    "Assistant",
    "What's wrong \n\nLet me know if you'd like me to help with anything else."
  ],
  "sentiment": {
    "score": 3,
    "analysis": "The sentiment in this exchange is neutral to slightly negative because the assistant is experiencing a problem (restarting), which may cause some inconvenience for the user. However, the assistant is trying to resolve the issue, which shows a proactive approach and can help maintain a positive user experience over time. Rating: 3"
  },
  "source": "swarm-intake"
}