{
  "text": "Our conversation has just begun. There is nothing to summarize yet, as I'm a large language model, I don't have any information or context about our previous conversation. What would you like to talk about?",
  "content": "ASSISTANT: [TOOL: Edit]",
  "namespace": "scripty",
  "username": "wolf",
  "session": "621bdaad-23c3-481e-9c72-341d424b2c88",
  "timestamp": "2025-12-29T08:57:58.163324",
  "keywords": [
    "Here are the extracted key topics/keywords in a comma-separated list:\n\nassistant",
    "tool",
    "edit"
  ],
  "sentiment": {
    "score": 3,
    "analysis": "In this conversation, there is no explicit emotional content or sentiment expressed, as the text only provides information about a tool's name. Therefore, it is not possible to accurately rate the sentiment based on this specific conversation. However, if we assume that the mention of an editing tool could be interpreted as neutral (3), since it doesn't inherently convey positive or negative emotions.\n\nIn a broader context, if a user were using this tool for productive purposes like writing or creating content, it might be rated higher (4) due to its functional value. On the other hand, if someone were struggling with the tool, they might rate it lower (2-1). However, these ratings are speculative and not based on the provided conversation itself."
  },
  "source": "swarm-intake"
}