{
  "text": "This conversation has just begun. There is no previous message to summarize or refer to, and you haven't mentioned Anaconda Python yet. I'm happy to chat with you about it now, though!",
  "content": "USER: should be using anaconda pythoin",
  "namespace": "scripty",
  "username": "wolf",
  "session": "c2917c9c-32f3-45db-afb0-553c39fb6eef",
  "timestamp": "2025-12-29T09:49:12.696179",
  "keywords": [
    "Here are the extracted keywords:\n\npython",
    "anaconda",
    "numpy",
    "pandas",
    "matplotlib",
    "scikit-learn"
  ],
  "sentiment": {
    "score": 3,
    "analysis": "The sentiment of the conversation is neutral as it is a factual statement without any emotional context or clear opinion. However, if we assume that the user's intention is to suggest using Anaconda for Python, then the sentiment can be rated slightly positive since Anaconda is a popular distribution of Python and its tools, making it easier to manage projects.\n\nRating: 3/5 (Neutral leaning slightly positive)"
  },
  "source": "swarm-intake"
}