{
  "text": "This conversation has just begun. There is nothing to summarize yet. I'm happy to chat with you, though! What would you like to talk about?",
  "content": "ASSISTANT: [TOOL: Task]",
  "namespace": "scripty",
  "username": "wolf",
  "session": "399a007e-72f9-443d-b3a6-480c54db5f4d",
  "timestamp": "2025-12-29T11:06:44.522058",
  "keywords": [
    "Here are the extracted keywords:\n\nassistant",
    "tool",
    "task"
  ],
  "sentiment": {
    "score": 3,
    "analysis": "In this specific exchange, there isn't enough context or emotional tone to accurately determine the sentiment. The assistant is simply stating a tool, which doesn't inherently carry a positive or negative connotation. Therefore, it would be difficult to rate the sentiment of this conversation on a scale of 1-5 as per the given criteria. However, if we consider the neutrality of the response, it could be considered as somewhat neutral (around 3)."
  },
  "source": "swarm-intake"
}